<?xml version="1.0" encoding="utf-8" ?>
<dwsync>
<file name="ckffolder.gif" server="200.195.178.52" local="131708030809402205" remote="131690691000000000" Dst="1" />
<file name="ckffolderopened.gif" server="200.195.178.52" local="131708030809830823" remote="131690691000000000" Dst="1" />
<file name="ckfminus.gif" server="200.195.178.52" local="131708030812277562" remote="131690691000000000" Dst="1" />
<file name="ckfnothumb.gif" server="200.195.178.52" local="131708030812859008" remote="131690691000000000" Dst="1" />
<file name="ckfplus.gif" server="200.195.178.52" local="131708030815846259" remote="131690691000000000" Dst="1" />
<file name="icons.png" server="200.195.178.52" local="131708030897050885" remote="131690691000000000" Dst="1" />
<file name="spacer.gif" server="200.195.178.52" local="131708030898843145" remote="131690691000000000" Dst="1" />
<file name="sprites_ie6.png" server="200.195.178.52" local="131708030899303410" remote="131690691000000000" Dst="1" />
<file name="sprites.png" server="200.195.178.52" local="131708030901054414" remote="131690691000000000" Dst="1" />
</dwsync>